README.md
setup.cfg
setup.py
packetracer/__init__.py
packetracer/checksum.py
packetracer/interceptor.py
packetracer/lazydict.py
packetracer/oui_stripped.txt
packetracer/packetracer.py
packetracer/packetracer_meta.py
packetracer/pcapng.py
packetracer/ppcap.py
packetracer/psocket.py
packetracer/statemachine.py
packetracer/structcbs.py
packetracer/triggerlist.py
packetracer/tuntap.py
packetracer/utils.py
packetracer.egg-info/PKG-INFO
packetracer.egg-info/SOURCES.txt
packetracer.egg-info/dependency_links.txt
packetracer.egg-info/requires.txt
packetracer.egg-info/top_level.txt
packetracer/layer12/__init__.py
packetracer/layer12/aoe.py
packetracer/layer12/arp.py
packetracer/layer12/btle.py
packetracer/layer12/can.py
packetracer/layer12/dtp.py
packetracer/layer12/ethernet.py
packetracer/layer12/flow_control.py
packetracer/layer12/ieee80211.py
packetracer/layer12/lacp.py
packetracer/layer12/linuxcc.py
packetracer/layer12/llc.py
packetracer/layer12/lldp.py
packetracer/layer12/ppp.py
packetracer/layer12/pppoe.py
packetracer/layer12/prism.py
packetracer/layer12/radiotap.py
packetracer/layer12/slac.py
packetracer/layer12/stp.py
packetracer/layer12/vrrp.py
packetracer/layer3/__init__.py
packetracer/layer3/esp.py
packetracer/layer3/icmp.py
packetracer/layer3/icmp6.py
packetracer/layer3/igmp.py
packetracer/layer3/ip.py
packetracer/layer3/ip6.py
packetracer/layer3/ip_shared.py
packetracer/layer3/ipx.py
packetracer/layer3/ospf.py
packetracer/layer3/pim.py
packetracer/layer4/__init__.py
packetracer/layer4/sctp.py
packetracer/layer4/ssl.py
packetracer/layer4/ssl_ciphersuites.py
packetracer/layer4/tcp.py
packetracer/layer4/udp.py
packetracer/layer567/__init__.py
packetracer/layer567/bgp.py
packetracer/layer567/der.py
packetracer/layer567/dhcp.py
packetracer/layer567/diameter.py
packetracer/layer567/dns.py
packetracer/layer567/hsrp.py
packetracer/layer567/http.py
packetracer/layer567/iso15118.py
packetracer/layer567/mqtt.py
packetracer/layer567/ntp.py
packetracer/layer567/pmap.py
packetracer/layer567/ptpv2.py
packetracer/layer567/radius.py
packetracer/layer567/rfb.py
packetracer/layer567/rip.py
packetracer/layer567/rtp.py
packetracer/layer567/sip.py
