Metadata-Version: 1.2
Name: packetracer
Version: 1.2
Summary: Packet Tracer: The fast and simple packet creating and parsing module
Home-page: https://github.com/hatamiarash7/PacketTracer
Author: Arash Hatami
Author-email: hatamiarash7@gmail.com
License: MIT
Platform: UNKNOWN
Classifier: Development Status :: 6 - Mature
Classifier: Intended Audience :: Developers
Classifier: License :: OSI Approved :: MIT License
Classifier: Natural Language :: English
Classifier: Programming Language :: Python :: 3.3
Classifier: Programming Language :: Python :: 3.4
Classifier: Programming Language :: Python :: 3.5
Classifier: Programming Language :: Python :: 3.6
Classifier: Programming Language :: Python :: Implementation :: CPython
Classifier: Programming Language :: Python :: Implementation :: PyPy
Requires-Python: >=3.3.*
